odoo10_addon_l10n_us_product-10.0.1.0.0-py2.7-nspkg.pth
odoo/addons/l10n_us_product/README.rst
odoo/addons/l10n_us_product/__init__.py
odoo/addons/l10n_us_product/__manifest__.py
odoo/addons/l10n_us_product/models/__init__.py
odoo/addons/l10n_us_product/models/product_template.py
odoo/addons/l10n_us_product/tests/__init__.py
odoo/addons/l10n_us_product/tests/test_product_template.py
odoo/addons/l10n_us_product/views/product_template_view.xml
odoo10_addon_l10n_us_product-10.0.1.0.0.dist-info/DESCRIPTION.rst
odoo10_addon_l10n_us_product-10.0.1.0.0.dist-info/METADATA
odoo10_addon_l10n_us_product-10.0.1.0.0.dist-info/RECORD
odoo10_addon_l10n_us_product-10.0.1.0.0.dist-info/WHEEL
odoo10_addon_l10n_us_product-10.0.1.0.0.dist-info/metadata.json
odoo10_addon_l10n_us_product-10.0.1.0.0.dist-info/namespace_packages.txt
odoo10_addon_l10n_us_product-10.0.1.0.0.dist-info/top_level.txt
